Workbook

Sheet Inputs
A1: Zetca credits and pricing: inputs
A2: Blue = an input you can change (yellow = the key levers). Black = formulas. Green = a link to the Inputs sheet. US dollars, as of 23 Oct 2026.
A4: Input | B4: Value | C4: Unit | D4: Source / note
A5: Bedrock input price (Claude Sonnet 4.6, US cross-region) | B5: 3.3 | C5: $ per million tokens | D5: AWS Price List API, AmazonBedrockFoundationModels, us-east-1, "Million Input Tokens Regional CRIS"
A6: Bedrock output price (Claude Sonnet 4.6, US cross-region) | B6: 16.5 | C6: $ per million tokens | D6: AWS Price List API, "Million Response Tokens Regional CRIS"
A7: Value of one Zetca credit | B7: 0.01 | C7: $ | D7: Proposed: 1 credit = 1 cent
A8: Margin on cost | B8: 0.4 | C8: % | D8: Proposed: covers card fees, server, storage, retries
A9: Minimum price per action | B9: 1 | C9: credits | D9: Proposed: the "small minimum"
A10: AWS Transcribe price | B10: 0.006 | C10: $ per minute of video | D10: aws.amazon.com/transcribe/pricing (US East): billed per second, no minimum
A11: Card fee, percentage | B11: 0.029 | C11: % of each payment | D11: Approximate Stripe standard rate; Paystack / Flutterwave differ
A12: Card fee, fixed | B12: 0.3 | C12: $ per payment | D12: Approximate Stripe standard rate
A13: Typical share of credits a user spends | B13: 0.5 | C13: % | D13: Assumption until the usage log has real data
A14: Lightsail server | B14: 12 | C14: $ a month | D14: terraform/variables.tf: small_3_0, 2 GB / 2 vCPU
A15: S3 + DynamoDB + other | B15: 6 | C15: $ a month | D15: Approximate at today's use
A16: Fixed costs a month | B16: =B14+B15

Sheet AI text actions
A1: What each AI text action costs (Bedrock) and its price
A2: Edit the token counts (blue) as the usage log gives real numbers. Cost = tokens x the prices on Inputs; price = cost x (1 + margin), rounded, never below the minimum.
A4: Action | B4: Input tokens | C4: Output tokens | D4: Cost to us ($) | E4: Price (credits) | F4: Price ($) | G4: Source
A5: Strategy (quiz) | B5: 2450 | C5: 1450 | D5: =(B5*Inputs!$B$5+C5*Inputs!$B$6)/1000000 | E5: =MAX(Inputs!$B$9,ROUND(D5*(1+Inputs!$B$8)/Inputs!$B$7,0)) | F5: =E5*Inputs!$B$7 | G5: measured, 10 runs
A6: Copywriter set, one platform (7 posts) | B6: 1900 | C6: 2600 | D6: =(B6*Inputs!$B$5+C6*Inputs!$B$6)/1000000 | E6: =MAX(Inputs!$B$9,ROUND(D6*(1+Inputs!$B$8)/Inputs!$B$7,0)) | F6: =E6*Inputs!$B$7 | G6: measured, 6 runs
A7: Copywriter set, X (7 short posts) | B7: 1905 | C7: 723 | D7: =(B7*Inputs!$B$5+C7*Inputs!$B$6)/1000000 | E7: =MAX(Inputs!$B$9,ROUND(D7*(1+Inputs!$B$8)/Inputs!$B$7,0)) | F7: =E7*Inputs!$B$7 | G7: measured
A8: Copywriter chat message | B8: 2300 | C8: 450 | D8: =(B8*Inputs!$B$5+C8*Inputs!$B$6)/1000000 | E8: =MAX(Inputs!$B$9,ROUND(D8*(1+Inputs!$B$8)/Inputs!$B$7,0)) | F8: =E8*Inputs!$B$7 | G8: measured, 2 runs
A9: Design words (text or stock visual) | B9: 1200 | C9: 160 | D9: =(B9*Inputs!$B$5+C9*Inputs!$B$6)/1000000 | E9: =MAX(Inputs!$B$9,ROUND(D9*(1+Inputs!$B$8)/Inputs!$B$7,0)) | F9: =E9*Inputs!$B$7 | G9: measured, 7 runs
A10: YouTube keywords | B10: 1000 | C10: 115 | D10: =(B10*Inputs!$B$5+C10*Inputs!$B$6)/1000000 | E10: =MAX(Inputs!$B$9,ROUND(D10*(1+Inputs!$B$8)/Inputs!$B$7,0)) | F10: =E10*Inputs!$B$7 | G10: measured
A11: YouTube title + description | B11: 900 | C11: 600 | D11: =(B11*Inputs!$B$5+C11*Inputs!$B$6)/1000000 | E11: =MAX(Inputs!$B$9,ROUND(D11*(1+Inputs!$B$8)/Inputs!$B$7,0)) | F11: =E11*Inputs!$B$7 | G11: estimate
A12: YouTube topics from transcript (10-min video) | B12: 3300 | C12: 300 | D12: =(B12*Inputs!$B$5+C12*Inputs!$B$6)/1000000 | E12: =MAX(Inputs!$B$9,ROUND(D12*(1+Inputs!$B$8)/Inputs!$B$7,0)) | F12: =E12*Inputs!$B$7 | G12: estimate
A13: YouTube titles + description from research | B13: 2500 | C13: 700 | D13: =(B13*Inputs!$B$5+C13*Inputs!$B$6)/1000000 | E13: =MAX(Inputs!$B$9,ROUND(D13*(1+Inputs!$B$8)/Inputs!$B$7,0)) | F13: =E13*Inputs!$B$7 | G13: estimate
A14: YouTube chapters (10-min video) | B14: 3000 | C14: 400 | D14: =(B14*Inputs!$B$5+C14*Inputs!$B$6)/1000000 | E14: =MAX(Inputs!$B$9,ROUND(D14*(1+Inputs!$B$8)/Inputs!$B$7,0)) | F14: =E14*Inputs!$B$7 | G14: estimate
A15: Auto-schedule | B15: 3000 | C15: 800 | D15: =(B15*Inputs!$B$5+C15*Inputs!$B$6)/1000000 | E15: =MAX(Inputs!$B$9,ROUND(D15*(1+Inputs!$B$8)/Inputs!$B$7,0)) | F15: =E15*Inputs!$B$7 | G15: estimate
A17: Full Copywriter set, four platforms (28 posts) | D17: =D6*3+D7 | E17: =MAX(Inputs!$B$9,ROUND(D17*(1+Inputs!$B$8)/Inputs!$B$7,0)) | F17: =E17*Inputs!$B$7 | G17: Instagram, LinkedIn and Facebook at the full-length rate, plus X

Sheet AI model catalog
A1: AI image and video models (Higgsfield): what each costs and its price
A2: Costs (blue) are Higgsfield estimate-endpoint figures for Zetca's account, 23 Oct 2026; edit them as prices change. 'Plans' (blue) says who can pick the model. Failed and blocked requests are not charged.
A4: Image model | B4: Maker | C4: Best for | D4: Setting | E4: Endpoint | F4: Cost per image ($) | G4: Price (credits) | H4: Price ($) | I4: Plans
A5: Soul V2 | B5: Higgsfield | C5: Portraits, fashion and editorial, with Soul styles (recommended default) | D5: 1080p | E5: /higgsfield-ai/soul/v2/standard | F5: 0.006 | G5: =MAX(Inputs!$B$9,ROUND(F5*(1+Inputs!$B$8)/Inputs!$B$7,0)) | H5: =G5*Inputs!$B$7 | I5: All paid
A6: Soul Cinema | B6: Higgsfield | C6: Cinema-style stills | D6: 1080p | E6: /higgsfield-ai/soul/cinema | F6: 0.006 | G6: =MAX(Inputs!$B$9,ROUND(F6*(1+Inputs!$B$8)/Inputs!$B$7,0)) | H6: =G6*Inputs!$B$7 | I6: All paid
A7: Z-Image Turbo | B7: Alibaba | C7: Fast images at 1K or 2K | D7: default | E7: /z-image/turbo | F7: 0.015 | G7: =MAX(Inputs!$B$9,ROUND(F7*(1+Inputs!$B$8)/Inputs!$B$7,0)) | H7: =G7*Inputs!$B$7 | I7: All paid
A8: Recraft V4.1 | B8: Recraft | C8: Design and illustration, palette and background control | D8: 1K | E8: /recraft/v4.1/text-to-image | F8: 0.035 | G8: =MAX(Inputs!$B$9,ROUND(F8*(1+Inputs!$B$8)/Inputs!$B$7,0)) | H8: =G8*Inputs!$B$7 | I8: All paid
A9: Recraft V4.1 Utility | B9: Recraft | C9: Same controls, utility style | D9: 1K | E9: /recraft/v4.1/utility/text-to-image | F9: 0.035 | G9: =MAX(Inputs!$B$9,ROUND(F9*(1+Inputs!$B$8)/Inputs!$B$7,0)) | H9: =G9*Inputs!$B$7 | I9: All paid
A10: Qwen Image 3 | B10: Alibaba | C10: Generate, or edit 1 to 3 reference images | D10: default | E10: /alibaba/qwen-image-3/text-to-image | F10: 0.04 | G10: =MAX(Inputs!$B$9,ROUND(F10*(1+Inputs!$B$8)/Inputs!$B$7,0)) | H10: =G10*Inputs!$B$7 | I10: All paid
A11: Ideogram 4.0 | B11: Ideogram | C11: Optional image reference, speed choice | D11: default | E11: /ideogram/v4.0 | F11: 0.06 | G11: =MAX(Inputs!$B$9,ROUND(F11*(1+Inputs!$B$8)/Inputs!$B$7,0)) | H11: =G11*Inputs!$B$7 | I11: All paid
A12: Grok Image 2.0 | B12: xAI | C12: Generate and edit with up to 10 references | D12: default | E12: /xai/grok-imagine-image-2.0 | F12: 0.06 | G12: =MAX(Inputs!$B$9,ROUND(F12*(1+Inputs!$B$8)/Inputs!$B$7,0)) | H12: =G12*Inputs!$B$7 | I12: All paid
A13: Soul (standard) | B13: Higgsfield | C13: Styles and style strength (used by the app today) | D13: 720p | E13: /higgsfield-ai/soul/standard | F13: 0.094 | G13: =MAX(Inputs!$B$9,ROUND(F13*(1+Inputs!$B$8)/Inputs!$B$7,0)) | H13: =G13*Inputs!$B$7 | I13: Pro, Agency
A14: Soul (standard) | B14: Higgsfield | C14: Styles and style strength (used by the app today) | D14: 1080p | E14: /higgsfield-ai/soul/standard | F14: 0.188 | G14: =MAX(Inputs!$B$9,ROUND(F14*(1+Inputs!$B$8)/Inputs!$B$7,0)) | H14: =G14*Inputs!$B$7 | I14: Pro, Agency
A15: Recraft V4.1 Pro | B15: Recraft | C15: 2K design and illustration | D15: 2K | E15: /recraft/v4.1/pro/text-to-image | F15: 0.21 | G15: =MAX(Inputs!$B$9,ROUND(F15*(1+Inputs!$B$8)/Inputs!$B$7,0)) | H15: =G15*Inputs!$B$7 | I15: Pro, Agency
A16: Recraft V4.1 Utility Pro | B16: Recraft | C16: 2K, utility style | D16: 2K | E16: /recraft/v4.1/utility/pro/text-to-image | F16: 0.21 | G16: =MAX(Inputs!$B$9,ROUND(F16*(1+Inputs!$B$8)/Inputs!$B$7,0)) | H16: =G16*Inputs!$B$7 | I16: Pro, Agency
A17: Marketing Studio 2.0 Alpha | B17: Higgsfield | C17: Campaign images with preset prompt boosts | D17: default | E17: /marketing-studio/image | F17: 0.373 | G17: =MAX(Inputs!$B$9,ROUND(F17*(1+Inputs!$B$8)/Inputs!$B$7,0)) | H17: =G17*Inputs!$B$7 | I17: Pro, Agency
A19: Videos are made by animating a first frame (Soul V2, row 5) with the video model, so a video costs the frame plus the video step.
A20: Video model (image to video) | B20: Maker | C20: Best for | D20: Length (s) | E20: Endpoint | F20: Video step ($) | G20: Video with first frame ($) | H20: Price (credits) | I20: Plans
A21: Kling 2.5 Turbo Standard | B21: Kling | C21: Low-cost clips (recommended default) | D21: 5 | E21: /kling-video/v2.5-turbo/standard/image-to-video | F21: 0.179 | G21: =F21+$F$5 | H21: =MAX(Inputs!$B$9,ROUND(G21*(1+Inputs!$B$8)/Inputs!$B$7,0)) | I21: All paid
A22: Hailuo 2.3 Standard | B22: MiniMax | C22: Text or image to video | D22: 6 | E22: /minimax/hailuo-2.3/standard/image-to-video | F22: 0.238 | G22: =F22+$F$5 | H22: =MAX(Inputs!$B$9,ROUND(G22*(1+Inputs!$B$8)/Inputs!$B$7,0)) | I22: All paid
A23: PixVerse V6 | B23: PixVerse | C23: Text or images, optional sound | D23: 5 | E23: /pixverse/v6/image-to-video | F23: 0.255 | G23: =F23+$F$5 | H23: =MAX(Inputs!$B$9,ROUND(G23*(1+Inputs!$B$8)/Inputs!$B$7,0)) | I23: All paid
A24: Kling 2.5 Turbo Pro | B24: Kling | C24: Higher quality Kling 2.5 | D24: 5 | E24: /kling-video/v2.5-turbo/pro/image-to-video | F24: 0.298 | G24: =F24+$F$5 | H24: =MAX(Inputs!$B$9,ROUND(G24*(1+Inputs!$B$8)/Inputs!$B$7,0)) | I24: All paid
A25: Wan 2.6 | B25: Alibaba | C25: Text, image or video references | D25: 5 | E25: /wan/v2.6/image-to-video | F25: 0.425 | G25: =F25+$F$5 | H25: =MAX(Inputs!$B$9,ROUND(G25*(1+Inputs!$B$8)/Inputs!$B$7,0)) | I25: Pro, Agency
A26: Wan 2.7 | B26: Alibaba | C26: Frames or multimodal references | D26: 5 | E26: /wan/v2.7/image-to-video | F26: 0.425 | G26: =F26+$F$5 | H26: =MAX(Inputs!$B$9,ROUND(G26*(1+Inputs!$B$8)/Inputs!$B$7,0)) | I26: Pro, Agency
A27: Kling 3.0 Turbo | B27: Kling | C27: Fast Kling 3.0 | D27: 5 | E27: /kling-video/v3.0-turbo/image-to-video | F27: 0.476 | G27: =F27+$F$5 | H27: =MAX(Inputs!$B$9,ROUND(G27*(1+Inputs!$B$8)/Inputs!$B$7,0)) | I27: Pro, Agency
A28: Wan 3.0 (720p list price) | B28: Alibaba | C28: Frames or multimodal references | D28: 5 | E28: /alibaba/wan-3.0/image-to-video | F28: 0.5 | G28: =F28+$F$5 | H28: =MAX(Inputs!$B$9,ROUND(G28*(1+Inputs!$B$8)/Inputs!$B$7,0)) | I28: Pro, Agency
A29: Kling 3.0 Standard | B29: Kling | C29: Kling 3.0 | D29: 5 | E29: /kling-video/v3.0/std/image-to-video | F29: 0.536 | G29: =F29+$F$5 | H29: =MAX(Inputs!$B$9,ROUND(G29*(1+Inputs!$B$8)/Inputs!$B$7,0)) | I29: Pro, Agency
A30: MiniMax H3 | B30: MiniMax | C30: Frames or multimodal references | D30: 5 | E30: /minimax/h3/image-to-video | F30: 0.553 | G30: =F30+$F$5 | H30: =MAX(Inputs!$B$9,ROUND(G30*(1+Inputs!$B$8)/Inputs!$B$7,0)) | I30: Pro, Agency
A31: Wan 3.0 Prime | B31: Alibaba | C31: Wan 3.0 Prime (price shows a 60% discount) | D31: 5 | E31: /alibaba/wan-3.0-prime/image-to-video | F31: 0.56 | G31: =F31+$F$5 | H31: =MAX(Inputs!$B$9,ROUND(G31*(1+Inputs!$B$8)/Inputs!$B$7,0)) | I31: Pro, Agency
A32: Happy Horse 1.0 | B32: Alibaba | C32: Text, a starting image or references | D32: 5 | E32: /alibaba/happy-horse/image-to-video | F32: 0.595 | G32: =F32+$F$5 | H32: =MAX(Inputs!$B$9,ROUND(G32*(1+Inputs!$B$8)/Inputs!$B$7,0)) | I32: Pro, Agency
... A38: Seedance 2.5 (720p, approximate) | B38: ByteDance | C38: Generate, edit and extend with references | D38: 5 | E38: /bytedance/seedance-2.5/image-to-video | F38: 2.311 | G38: =F38+$F$5 | H38: =MAX(Inputs!$B$9,ROUND(G38*(1+Inputs!$B$8)/Inputs!$B$7,0)) | I38: Agency
A40: Most video prices include a 15% Higgsfield discount that may be temporary.
A41: Not priced: Marketing Studio 2.5 Flare and Sunburst (token-metered), Seedance 2.0 (token-metered), reference and edit workflows, Cinema Studio, Genjutsu, Grok Imagine Video.
A42: Text-to-video variants cost the same as image to video but most can't set a 9:16 shape, so Zetca animates a first frame instead.

Sheet YouTube suggestions
A1: YouTube suggestions: cost per minute of video
A2: Transcribe is charged per minute; the AI steps grow with the transcript. Edit the token estimates (blue).
A4: Item | B4: Value | C4: Unit
A5: Transcribe | B5: =Inputs!$B$10 | C5: $ a minute
A6: AI input tokens per minute of video | B6: 900 | C6: tokens
A7: AI output tokens per minute of video | B7: 60 | C7: tokens
A8: AI cost per minute | B8: =(B6*Inputs!$B$5+B7*Inputs!$B$6)/1000000 | C8: $ a minute
A9: Cost per minute of video | B9: =B5+B8 | C9: $ a minute
A10: Price per minute | B10: =B9*(1+Inputs!$B$8)/Inputs!$B$7 | C10: credits
A11: Minimum price per video | B11: 5 | C11: credits
A13: Video length (minutes) | B13: Cost to us ($) | C13: Price (credits)
A14: 5 | B14: =A14*$B$9 | C14: =MAX($B$11,ROUND(A14*$B$10,0))
A15: 10 | B15: =A15*$B$9 | C15: =MAX($B$11,ROUND(A15*$B$10,0))
A16: 20 | B16: =A16*$B$9 | C16: =MAX($B$11,ROUND(A16*$B$10,0))
A17: 30 | B17: =A17*$B$9 | C17: =MAX($B$11,ROUND(A17*$B$10,0))
A18: 60 | B18: =A18*$B$9 | C18: =MAX($B$11,ROUND(A18*$B$10,0))

Sheet Plans
A1: Plans: price, credits and margin
A2: Margin = price minus card fees minus the AI cost of the credits used. Credits are priced at cost x (1 + margin), so their cost = credits x credit value / (1 + margin).
A4: Plan | B4: Price a month ($) | C4: Credits | D4: AI images + videos | E4: Card fees ($) | F4: Cost if all credits used ($) | G4: Margin if all used ($) | H4: Margin if all used (%) | I4: Cost at typical use ($) | J4: Margin at typical use ($) | K4: Margin at typical use (%)
A5: Free | B5: 0 | C5: 100 | D5: no | E5: =IF(B5>0,B5*Inputs!$B$11+Inputs!$B$12,0) | F5: =C5*Inputs!$B$7/(1+Inputs!$B$8) | G5: =B5-E5-F5 | H5: =IF(B5>0,G5/B5,0) | I5: =F5*Inputs!$B$13 | J5: =B5-E5-I5 | K5: =IF(B5>0,J5/B5,0)
A6: Starter | B6: 15 | C6: 1500 | D6: yes | E6: =IF(B6>0,B6*Inputs!$B$11+Inputs!$B$12,0) | F6: =C6*Inputs!$B$7/(1+Inputs!$B$8) | G6: =B6-E6-F6 | H6: =IF(B6>0,G6/B6,0) | I6: =F6*Inputs!$B$13 | J6: =B6-E6-I6 | K6: =IF(B6>0,J6/B6,0)
A7: Pro | B7: 39 | C7: 4000 | D7: yes | E7: =IF(B7>0,B7*Inputs!$B$11+Inputs!$B$12,0) | F7: =C7*Inputs!$B$7/(1+Inputs!$B$8) | G7: =B7-E7-F7 | H7: =IF(B7>0,G7/B7,0) | I7: =F7*Inputs!$B$13 | J7: =B7-E7-I7 | K7: =IF(B7>0,J7/B7,0)
A8: Agency | B8: 99 | C8: 10000 | D8: yes | E8: =IF(B8>0,B8*Inputs!$B$11+Inputs!$B$12,0) | F8: =C8*Inputs!$B$7/(1+Inputs!$B$8) | G8: =B8-E8-F8 | H8: =IF(B8>0,G8/B8,0) | I8: =F8*Inputs!$B$13 | J8: =B8-E8-I8 | K8: =IF(B8>0,J8/B8,0)
A9: Top-up 500 | B9: 6 | C9: 500 | D9: yes | E9: =IF(B9>0,B9*Inputs!$B$11+Inputs!$B$12,0) | F9: =C9*Inputs!$B$7/(1+Inputs!$B$8) | G9: =B9-E9-F9 | H9: =IF(B9>0,G9/B9,0) | I9: =F9*Inputs!$B$13 | J9: =B9-E9-I9 | K9: =IF(B9>0,J9/B9,0)
A10: Top-up 2,000 | B10: 22 | C10: 2000 | D10: yes | E10: =IF(B10>0,B10*Inputs!$B$11+Inputs!$B$12,0) | F10: =C10*Inputs!$B$7/(1+Inputs!$B$8) | G10: =B10-E10-F10 | H10: =IF(B10>0,G10/B10,0) | I10: =F10*Inputs!$B$13 | J10: =B10-E10-I10 | K10: =IF(B10>0,J10/B10,0)
A12: Starter subscribers to cover fixed costs | B12: =ROUNDUP(Inputs!$B$16/J6,0) | C12: at typical use
